testgres/__init__.py
testgres/api.py
testgres/backup.py
testgres/cache.py
testgres/config.py
testgres/connection.py
testgres/consts.py
testgres/decorators.py
testgres/defaults.py
testgres/enums.py
testgres/exceptions.py
testgres/logger.py
testgres/node.py
testgres/node_app.py
testgres/port_manager.py
testgres/pubsub.py
testgres/raise_error.py
testgres/standby.py
testgres/utils.py
testgres/impl/port_manager__generic.py
testgres/impl/port_manager__this_host.py
testgres-1.13.4.dist-info/licenses/LICENSE
testgres-1.13.4.dist-info/METADATA
testgres-1.13.4.dist-info/WHEEL
testgres-1.13.4.dist-info/top_level.txt
testgres-1.13.4.dist-info/RECORD
