Metadata-Version: 2.4
Name: testgres
Version: 1.13.4
Summary: Testing utility for PostgreSQL and its extensions
Author-email: Postgres Professional <testgres@postgrespro.ru>
License: PostgreSQL
Project-URL: HomePage, https://github.com/postgrespro/testgres
Keywords: test,testing,postgresql
Classifier: Intended Audience :: Developers
Classifier: Operating System :: Unix
Classifier: Programming Language :: Python :: 3 :: Only
Classifier: Programming Language :: Python :: 3.7
Classifier: Programming Language :: Python :: 3.8
Classifier: Programming Language :: Python :: 3.9
Classifier: Programming Language :: Python :: 3.10
Classifier: Programming Language :: Python :: 3.11
Classifier: Programming Language :: Python :: 3.12
Classifier: Programming Language :: Python :: 3.13
Classifier: Programming Language :: Python :: 3.14
Classifier: Topic :: Software Development :: Libraries
Classifier: Topic :: Software Development :: Testing
Requires-Python: >=3.7.3
License-File: LICENSE
Requires-Dist: pg8000
Requires-Dist: port-for>=0.4
Requires-Dist: six>=1.9.0
Requires-Dist: psutil
Requires-Dist: packaging
Requires-Dist: testgres.os_ops<3.0.0,>=2.0.2
Dynamic: license-file
